setup.py
alibaba/__init__.py
alibaba/cache.py
alibaba/fetch.py
alibaba/pic.py
alibaba/storage.py
alibaba/tmp/__init__.py
alibaba_python_sdk.egg-info/PKG-INFO
alibaba_python_sdk.egg-info/SOURCES.txt
alibaba_python_sdk.egg-info/dependency_links.txt
alibaba_python_sdk.egg-info/top_level.txt