Metadata-Version: 1.0
Name: alibaba-python-sdk
Version: 0.1.3
Summary: Aibaba SDK for python.
Home-page: UNKNOWN
Author: chenqiu
Author-email: UNKNOWN
License: GPL version 2
Platform: UNKNOWN
